[
 	{
		"table":"YouTube Transkrib",
		"map":[
			{
				"from":"URL_video",
				"to":"url"
			},
			{
				"from":"Text",
				"to":"description"
			},
			{
				"from":"Avtor",
				"to":"blogger",
				"verify_for_null":true
			}


		]
	},
 	{
		"table":"Transkrib_TikTok",
		"map":[
			{
				"from":"video_url",
				"to":"url"
			},
			{
				"from":"text",
				"to":"description"
			},
			{
				"from":"author_name",
				"to":"blogger",
				"verify_for_null":true
			}
		]
	},
 	{
		"table":"transkrib_insta",
		"neq":{
			"column":"Text",
			"value":"Ошибка"
		},
		"map":[
			{
				"from":"Video_Url",
				"to":"url"
			},
			{
				"from":"Text",
				"to":"description"
			},
			{
				"from":"author",
				"to":"blogger",
				"verify_for_null":true
			}


		]
	}
]